Metadata-Version: 2.1
Name: jirasession
Version: 0.2.3
Summary: A light weight library to interact with the Jira API
Home-page: https://www.github.com/tannerburns/jirasession
Author: Tanner Burns
Author-email: tjburns102@gmail.com
License: UNKNOWN
Platform: UNKNOWN
Classifier: Operating System :: OS Independent
Classifier: Programming Language :: Python :: 3.7
